README
setup.py
bambu_urlshortener/__init__.py
bambu_urlshortener/admin.py
bambu_urlshortener/apps.py
bambu_urlshortener/middleware.py
bambu_urlshortener/models.py
bambu_urlshortener.egg-info/PKG-INFO
bambu_urlshortener.egg-info/SOURCES.txt
bambu_urlshortener.egg-info/dependency_links.txt
bambu_urlshortener.egg-info/requires.txt
bambu_urlshortener.egg-info/top_level.txt
bambu_urlshortener/migrations/0001_initial.py
bambu_urlshortener/migrations/__init__.py
bambu_urlshortener/providers/__init__.py
bambu_urlshortener/providers/bitly.py
bambu_urlshortener/providers/db.py