Metadata-Version: 1.1
Name: bambu-urlshortener
Version: 2.0
Summary: Shrink a URL using an internal or external shortening service
Home-page: https://github.com/iamsteadman/bambu-urlshortener
Author: Steadman
Author-email: mark@steadman.io
License: UNKNOWN
Platform: UNKNOWN
Classifier: Development Status :: 4 - Beta
Classifier: Environment :: Web Environment
Classifier: Framework :: Django
